contiguity/__init__.py
contiguity/_auth.py
contiguity/_client.py
contiguity/_instant_messaging.py
contiguity/_product.py
contiguity/_response.py
contiguity/domains.py
contiguity/email.py
contiguity/identity.py
contiguity/imessage.py
contiguity/leases.py
contiguity/otp.py
contiguity/py.typed
contiguity/text.py
contiguity/verify.py
contiguity/whatsapp.py
contiguity/base/__init__.py
contiguity/base/async_base.py
contiguity/base/base.py
contiguity/base/common.py
contiguity/base/exceptions.py
contiguity-3.0.0.dist-info/licenses/LICENSE.txt
contiguity-3.0.0.dist-info/METADATA
contiguity-3.0.0.dist-info/WHEEL
contiguity-3.0.0.dist-info/top_level.txt
contiguity-3.0.0.dist-info/RECORD
