Metadata-Version: 2.4
Name: contiguity
Version: 3.0.0
Summary: Contiguity's official Python SDK
Author-email: Contiguity <help@contiguity.support>
License: MIT License
Project-URL: Repository, https://github.com/contiguity/python
Keywords: python,contiguity,sms,email,otp,deta,base,database
Classifier: Development Status :: 3 - Alpha
Classifier: Intended Audience :: Developers
Classifier: License :: OSI Approved :: MIT License
Classifier: Operating System :: OS Independent
Classifier: Programming Language :: Python :: 3
Classifier: Topic :: Utilities
Classifier: Typing :: Typed
Requires-Python: >=3.10
License-File: LICENSE.txt
Requires-Dist: httpx>=0.27.2
Requires-Dist: msgspec>=0.19.0
Requires-Dist: phonenumbers<10.0.0,>=9.0.15
Requires-Dist: typing-extensions<5.0.0,>=4.12.2
Dynamic: license-file
